{"updated":1590776622521,"numeroAtivos":null,"numeroEstados":null,"ativos":[],"preco":71.97,"variacao":-0.04,"liquidezDiaria":2402,"ultimoRendimento":0.24,"yield":0.31,"patrimonioLiquido":58000000,"valorPatrimonial":87.42,"rentabilidadeMes":0.02,"pVpa":0.82,"informacoesBasicas":{"razaoSocial":"FDO INV. IMOB. FOF INTEGRAL BREI","dataConstituicao":"N/A","numeroCotas":666681,"patrimonioInicial":null,"valorInicial":null,"tipoGestao":"Ativa","taxaPerformace":20,"taxaGestao":0.8,"cnpj":"33.721.517/0001-29","publicoAlvo":"Investidores em Geral","mandato":"Renda","segmento":"Títulos e Val. Mob.","prazoDuracao":"Indeterminado","taxaAdministracao":0.2,"taxaGerenciamento":null,"taxaConsultoria":null}}