{"updated":1590535601754,"numeroAtivos":3,"numeroEstados":2,"ativos":[{"nome":"Ed. Empr. Center I","endereco":"R. Padre Carapuceiro, 733","bairro":"","cidade":"Recife - PE","areaLocavel":"4.248,00 m2"},{"nome":"Ed. Empr. Center II","endereco":"R. Antonio Lumack de Monte, 96","bairro":"","cidade":"Recife - PE","areaLocavel":"4.035,00 m2"},{"nome":"Ed. Suarez Trade","endereco":"Av. Tancredo Neves, 450","bairro":"","cidade":"Salvador - BA","areaLocavel":"4.620,00 m2"}],"preco":62.4,"variacao":0,"liquidezDiaria":66,"ultimoRendimento":0.04,"yield":0.06,"patrimonioLiquido":66000000,"valorPatrimonial":89.32,"rentabilidadeMes":0.06,"pVpa":0.7,"informacoesBasicas":{"razaoSocial":"NEWPORT RENDA URBANA FDO INV IMOB","dataConstituicao":"20 de Dezembro de 2011","numeroCotas":742000,"patrimonioInicial":74200000,"valorInicial":100,"tipoGestao":"Passiva","taxaPerformace":null,"taxaGestao":null,"cnpj":"14.793.782/0001-78","publicoAlvo":"Investidores em Geral","mandato":"Renda","segmento":"Lajes Corporativas","prazoDuracao":"Indeterminado","taxaAdministracao":0.48,"taxaGerenciamento":null,"taxaConsultoria":null}}