{"updated":1590535613540,"numeroAtivos":null,"numeroEstados":null,"ativos":[],"preco":83.49,"variacao":5.62,"liquidezDiaria":10,"ultimoRendimento":0.34,"yield":0.42,"patrimonioLiquido":81000000,"valorPatrimonial":97.84,"rentabilidadeMes":-3.72,"pVpa":0.85,"informacoesBasicas":{"razaoSocial":"VOTORANTIM SECURITIES MASTER FDO INV IMOB - FII","dataConstituicao":"N/A","numeroCotas":827913,"patrimonioInicial":null,"valorInicial":null,"tipoGestao":"Ativa","taxaPerformace":null,"taxaGestao":null,"cnpj":"17.870.926/0001-30","publicoAlvo":"Investidores em Geral","mandato":"Títulos e Valores Mobiliários","segmento":"Títulos e Val. Mob.","prazoDuracao":"Indeterminado","taxaAdministracao":null,"taxaGerenciamento":null,"taxaConsultoria":null}}